nexy/__init__.py
nexy/__main__.py
nexy/app.py
nexy/decorators.py
nexy/hooks.py
nexy/router.py
nexy/utils.py
nexy/cli/__init__.py
nexy/cli/commands/__init__.py
nexy/cli/commands/add.py
nexy/cli/commands/build.py
nexy/cli/commands/dev.py
nexy/cli/commands/generate.py
nexy/cli/commands/init.py
nexy/cli/commands/install.py
nexy/cli/commands/new.py
nexy/cli/commands/serve.py
nexy/cli/commands/update.py
nexy/cli/commands/upgrade.py
nexy/cli/core/__init__.py
nexy/cli/core/constants.py
nexy/cli/core/models.py
nexy/cli/core/project_builder.py
nexy/cli/core/utils.py
nexy-0.1.8.dist-info/METADATA
nexy-0.1.8.dist-info/WHEEL
nexy-0.1.8.dist-info/entry_points.txt
nexy-0.1.8.dist-info/licenses/LICENSE
nexy-0.1.8.dist-info/RECORD
