Metadata-Version: 2.4
Name: nexy
Version: 0.1.8
Summary: Nexy a Python framework designed to combine simplicity, performance, and the joy of development.
Project-URL: Homepage, https://docs-nexy.vercel.app/docs/started
Project-URL: Repository, https://github.com/NexyPy/Nexy
Project-URL: PyPI, https://pypi.org/project/nexy/
Author-email: Espoir-Loemba <hopcy.forcy@gmail.com>
License-File: LICENSE
Classifier: Development Status :: 4 - Beta
Classifier: Intended Audience :: Developers
Classifier: License :: OSI Approved :: MIT License
Classifier: Programming Language :: Python :: 3
Classifier: Programming Language :: Python :: 3.12
Requires-Python: >=3.12
Requires-Dist: fastapi<1.0.0,>=0.115.0
Requires-Dist: h11<0.15
Requires-Dist: inquirerpy==0.3.4
Requires-Dist: jinja2<4.0.0,>=3.1.0
Requires-Dist: pyjwt<3.0.0,>=2.8.0
Requires-Dist: scalar-fastapi
Requires-Dist: typer>=0.12.0
Requires-Dist: uvicorn<1.0.0,>=0.29.0
